recaptchav3ninja/__init__.py
recaptchav3ninja/ninja.py
recaptchav3ninja-1.0.1.dist-info/LICENSE
recaptchav3ninja-1.0.1.dist-info/METADATA
recaptchav3ninja-1.0.1.dist-info/WHEEL
recaptchav3ninja-1.0.1.dist-info/top_level.txt
recaptchav3ninja-1.0.1.dist-info/RECORD
